pythonium/__init__.py
pythonium/__main__.py
pythonium/main.py
pythonium/common/__init__.py
pythonium/common/async_file_ops.py
pythonium/common/base.py
pythonium/common/config.py
pythonium/common/error_handling.py
pythonium/common/events.py
pythonium/common/exceptions.py
pythonium/common/http.py
pythonium/common/logging.py
pythonium/common/parameters.py
pythonium/common/types.py
pythonium/common/llm/__init__.py
pythonium/common/llm/client.py
pythonium/core/__init__.py
pythonium/core/config.py
pythonium/core/managers.py
pythonium/core/server.py
pythonium/core/tools/__init__.py
pythonium/core/tools/discovery.py
pythonium/core/tools/registry.py
pythonium/managers/__init__.py
pythonium/managers/base.py
pythonium/tools/__init__.py
pythonium/tools/base.py
pythonium/tools/std/__init__.py
pythonium/tools/std/execution.py
pythonium/tools/std/file_ops.py
pythonium/tools/std/parameters.py
pythonium/tools/std/tool_ops.py
pythonium/tools/std/web.py
pythonium-0.1.5.dist-info/licenses/LICENSE
pythonium-0.1.5.dist-info/METADATA
pythonium-0.1.5.dist-info/WHEEL
pythonium-0.1.5.dist-info/entry_points.txt
pythonium-0.1.5.dist-info/top_level.txt
pythonium-0.1.5.dist-info/RECORD
