Metadata-Version: 2.4
Name: pythonium
Version: 0.1.5
Summary: A modular MCP (Model Context Protocol) server for AI agents with plugin-based architecture
Author-email: David Harvey <dwh.exis@gmail.com>
License-Expression: MIT
Project-URL: Homepage, https://github.com/dwharve/pythonium
Project-URL: Bug Reports, https://github.com/dwharve/pythonium/issues
Project-URL: Source, https://github.com/dwharve/pythonium
Project-URL: Documentation, https://pythonium.readthedocs.io/
Keywords: mcp,model-context-protocol,ai-agents,plugin-framework,server,artificial-intelligence,tools
Classifier: Development Status :: 4 - Beta
Classifier: Intended Audience :: Developers
Classifier: Intended Audience :: Information Technology
Classifier: Operating System :: OS Independent
Classifier: Programming Language :: Python :: 3
Classifier: Programming Language :: Python :: 3.8
Classifier: Programming Language :: Python :: 3.9
Classifier: Programming Language :: Python :: 3.10
Classifier: Programming Language :: Python :: 3.11
Classifier: Programming Language :: Python :: 3.12
Classifier: Topic :: Software Development :: Libraries :: Python Modules
Classifier: Topic :: Internet :: WWW/HTTP :: HTTP Servers
Classifier: Topic :: System :: Distributed Computing
Classifier: Topic :: Scientific/Engineering :: Artificial Intelligence
Classifier: Topic :: Software Development :: Libraries :: Application Frameworks
Requires-Python: >=3.8
License-File: LICENSE
Requires-Dist: pydantic>=2.0.0
Requires-Dist: pydantic-settings>=2.0.0
Requires-Dist: pyyaml>=6.0
Requires-Dist: click>=8.0.0
Requires-Dist: rich>=13.0.0
Requires-Dist: loguru>=0.7.0
Requires-Dist: httpx>=0.24.0
Requires-Dist: beautifulsoup4>=4.12.0
Requires-Dist: mcp>=1.10.0
Requires-Dist: langgraph>=0.2.0
Requires-Dist: orjson>=3.8.0
Requires-Dist: aiofiles>=23.0.0
Provides-Extra: dev
Requires-Dist: pytest>=7.0.0; extra == "dev"
Requires-Dist: pytest-asyncio>=0.21.0; extra == "dev"
Requires-Dist: pytest-cov>=4.0.0; extra == "dev"
Requires-Dist: pytest-mock>=3.10.0; extra == "dev"
Requires-Dist: black>=23.0.0; extra == "dev"
Requires-Dist: isort>=5.12.0; extra == "dev"
Requires-Dist: flake8>=6.0.0; extra == "dev"
Requires-Dist: mypy>=1.0.0; extra == "dev"
Requires-Dist: pre-commit>=3.0.0; extra == "dev"
Requires-Dist: tox>=4.0.0; extra == "dev"
Provides-Extra: docs
Requires-Dist: sphinx>=5.0.0; extra == "docs"
Requires-Dist: sphinx-rtd-theme>=1.2.0; extra == "docs"
Requires-Dist: myst-parser>=1.0.0; extra == "docs"
Provides-Extra: testing
Requires-Dist: pytest>=7.0.0; extra == "testing"
Requires-Dist: pytest-asyncio>=0.21.0; extra == "testing"
Requires-Dist: pytest-cov>=4.0.0; extra == "testing"
Requires-Dist: pytest-mock>=3.10.0; extra == "testing"
Requires-Dist: httpx>=0.24.0; extra == "testing"
Provides-Extra: build
Requires-Dist: build>=0.10.0; extra == "build"
Requires-Dist: twine>=4.0.0; extra == "build"
Requires-Dist: wheel>=0.40.0; extra == "build"
Provides-Extra: all
Requires-Dist: pythonium[build,dev,docs,testing]; extra == "all"
Dynamic: license-file
